monolithic/__init__.py
monolithic/cli.py
monolithic/monolithic.py
monolithic-0.1.0.dist-info/entry_points.txt
monolithic-0.1.0.dist-info/LICENSE
monolithic-0.1.0.dist-info/WHEEL
monolithic-0.1.0.dist-info/METADATA
monolithic-0.1.0.dist-info/RECORD
